{
  "name": "iv_overlap_relief_partnership",
  "elements": [
    {
      "seq_no": 1,
      "tie_breaker": 1,
      "name": "MR*B*HAM",
      "utr": 8900000456,
      "nino": "BL987567Z",
      "partnership_ref_number": 8834567014,
      "date_you_became_a_partner": "2016-08-21T00:00:00",
      "date_you_left_the_partnership": "2023-10-14T00:00:00",
      "basis_period_starts": "2018-07-27T00:00:00",
      "basis_period_ends": "2019-06-01T00:00:00",
      "share_of_profit_or_loss": 54361,
      "net_business_loss_partners": 543,
      "overlap_relief_used_this_year": 765,
      "overlap_profit_carried_forward": 4,
      "tax_year": 2023,
      "links": [
        {
          "rel": "self",
          "href": "https://vdp.dev.denodo.hip.ns2n.corp.hmrc.gov.uk:9443/server/basis_period_reform/ws_overlap_relief_partnership/views/iv_overlap_relief_partnership/8900000456,8834567014"
        }
      ]
    }
  ],
  "links": [
    {
      "rel": "self",
      "href": "https://vdp.dev.denodo.hip.ns2n.corp.hmrc.gov.uk:9443/server/basis_period_reform/ws_overlap_relief_partnership/views/iv_overlap_relief_partnership?utr=8900000456&partnership_ref_number=8834567014"
    }
  ]
}
